numpngw.py
numpngw-0.1.4.dist-info/LICENSE.txt
numpngw-0.1.4.dist-info/METADATA
numpngw-0.1.4.dist-info/WHEEL
numpngw-0.1.4.dist-info/top_level.txt
numpngw-0.1.4.dist-info/RECORD
