Metadata-Version: 2.1
Name: numpngw
Version: 0.1.4
Summary: Write numpy array(s) to a PNG or animated PNG file.
Home-page: https://github.com/WarrenWeckesser/numpngw
Author: Warren Weckesser
License: BSD
Keywords: numpy png matplotlib animation
Classifier: License :: OSI Approved :: BSD License
Classifier: Intended Audience :: Developers
Classifier: Operating System :: OS Independent
Classifier: Programming Language :: Python :: 3
Classifier: Programming Language :: Python :: 3.7
Classifier: Programming Language :: Python :: 3.8
Classifier: Programming Language :: Python :: 3.9
Classifier: Programming Language :: Python :: 3.10
Classifier: Programming Language :: Python :: 3.11
Classifier: Programming Language :: Python :: 3.12
License-File: LICENSE.txt
Requires-Dist: numpy>=1.6.0
